bestehorn_llmmanager/__init__.py
bestehorn_llmmanager/_version.py
bestehorn_llmmanager/llm_manager.py
bestehorn_llmmanager/message_builder.py
bestehorn_llmmanager/message_builder_constants.py
bestehorn_llmmanager/message_builder_enums.py
bestehorn_llmmanager/parallel_llm_manager.py
bestehorn_llmmanager/py.typed
bestehorn_llmmanager/bedrock/CRISManager.py
bestehorn_llmmanager/bedrock/ModelManager.py
bestehorn_llmmanager/bedrock/UnifiedModelManager.py
bestehorn_llmmanager/bedrock/__init__.py
bestehorn_llmmanager/bedrock/auth/__init__.py
bestehorn_llmmanager/bedrock/auth/auth_manager.py
bestehorn_llmmanager/bedrock/builders/__init__.py
bestehorn_llmmanager/bedrock/builders/parameter_builder.py
bestehorn_llmmanager/bedrock/cache/__init__.py
bestehorn_llmmanager/bedrock/cache/cache_point_manager.py
bestehorn_llmmanager/bedrock/catalog/__init__.py
bestehorn_llmmanager/bedrock/catalog/alias_generators.py
bestehorn_llmmanager/bedrock/catalog/api_fetcher.py
bestehorn_llmmanager/bedrock/catalog/bedrock_catalog.py
bestehorn_llmmanager/bedrock/catalog/bundled_loader.py
bestehorn_llmmanager/bedrock/catalog/cache_manager.py
bestehorn_llmmanager/bedrock/catalog/legacy_name_mapper.py
bestehorn_llmmanager/bedrock/catalog/legacy_name_mappings.py
bestehorn_llmmanager/bedrock/catalog/name_normalizer.py
bestehorn_llmmanager/bedrock/catalog/name_resolution_structures.py
bestehorn_llmmanager/bedrock/catalog/name_resolver.py
bestehorn_llmmanager/bedrock/catalog/transformer.py
bestehorn_llmmanager/bedrock/correlators/__init__.py
bestehorn_llmmanager/bedrock/correlators/model_cris_correlator.py
bestehorn_llmmanager/bedrock/discovery/__init__.py
bestehorn_llmmanager/bedrock/discovery/region_discovery.py
bestehorn_llmmanager/bedrock/distributors/__init__.py
bestehorn_llmmanager/bedrock/distributors/region_distribution_manager.py
bestehorn_llmmanager/bedrock/downloaders/__init__.py
bestehorn_llmmanager/bedrock/downloaders/base_downloader.py
bestehorn_llmmanager-0.7.3.dist-info/LICENSE
bestehorn_llmmanager-0.7.3.dist-info/METADATA
bestehorn_llmmanager-0.7.3.dist-info/WHEEL
bestehorn_llmmanager-0.7.3.dist-info/top_level.txt
bestehorn_llmmanager-0.7.3.dist-info/RECORD
