Metadata-Version: 2.1
Name: bestehorn-llmmanager
Version: 0.7.3
Summary: A comprehensive Python library for managing AWS Bedrock Converse API interactions with multi-model support, intelligent retry logic, and parallel processing capabilities
Author-email: Markus Bestehorn <markus.bestehorn@googlemail.com>
Maintainer-email: Markus Bestehorn <markus.bestehorn@googlemail.com>
License: MIT
Project-URL: Homepage, https://github.com/Bestehorn/LLMManager
Project-URL: Documentation, https://github.com/Bestehorn/LLMManager/blob/main/README.md
Project-URL: Repository, https://github.com/Bestehorn/LLMManager.git
Project-URL: Bug Tracker, https://github.com/Bestehorn/LLMManager/issues
Keywords: aws,bedrock,llm,ai,machine-learning,amazon,claude,anthropic
Classifier: Development Status :: 4 - Beta
Classifier: Intended Audience :: Developers
Classifier: License :: OSI Approved :: MIT License
Classifier: Operating System :: OS Independent
Classifier: Programming Language :: Python :: 3
Classifier: Programming Language :: Python :: 3.9
Classifier: Programming Language :: Python :: 3.10
Classifier: Programming Language :: Python :: 3.11
Classifier: Programming Language :: Python :: 3.12
Classifier: Topic :: Software Development :: Libraries :: Python Modules
Classifier: Topic :: Software Development :: Libraries
Classifier: Topic :: Software Development :: Libraries :: Application Frameworks
Classifier: Topic :: System :: Distributed Computing
Classifier: Topic :: Text Processing :: Linguistic
Classifier: Topic :: Internet :: WWW/HTTP :: Dynamic Content
Classifier: Topic :: Scientific/Engineering :: Artificial Intelligence
Classifier: Natural Language :: English
Classifier: Typing :: Typed
Requires-Python: <4.0,>=3.9
License-File: LICENSE
Requires-Dist: boto3>=1.28.0
Requires-Dist: botocore>=1.31.0
Requires-Dist: beautifulsoup4>=4.12.0
Requires-Dist: lxml>=4.9.0
Requires-Dist: requests>=2.31.0
Requires-Dist: tenacity>=8.2.0
Provides-Extra: dev
Requires-Dist: pytest>=7.4.0; extra == "dev"
Requires-Dist: pytest-cov>=4.1.0; extra == "dev"
Requires-Dist: pytest-mock>=3.11.1; extra == "dev"
Requires-Dist: pytest-asyncio>=0.21.0; extra == "dev"
Requires-Dist: pytest-html>=3.2.0; extra == "dev"
Requires-Dist: pytest-xdist>=3.3.1; extra == "dev"
Requires-Dist: coverage>=7.3.0; extra == "dev"
Requires-Dist: responses>=0.23.3; extra == "dev"
Requires-Dist: freezegun>=1.2.2; extra == "dev"
Requires-Dist: factory-boy>=3.3.0; extra == "dev"
Requires-Dist: ipykernel>=6.25.0; extra == "dev"
Requires-Dist: black>=23.0.0; extra == "dev"
Requires-Dist: isort>=5.12.0; extra == "dev"
Requires-Dist: flake8>=6.0.0; extra == "dev"
Requires-Dist: mypy>=1.5.0; extra == "dev"
Requires-Dist: pre-commit>=3.3.0; extra == "dev"
Requires-Dist: hypothesis>=6.82.0; extra == "dev"
Requires-Dist: bandit>=1.7.5; extra == "dev"
Requires-Dist: boto3-stubs[bedrock-runtime]>=1.28.0; extra == "dev"
Provides-Extra: docs
Requires-Dist: sphinx>=7.0.0; extra == "docs"
Requires-Dist: sphinx-rtd-theme>=1.3.0; extra == "docs"
Requires-Dist: sphinx-autodoc-typehints>=1.24.0; extra == "docs"
